ballcosmos/__init__.py
ballcosmos/__version__.py
ballcosmos/api_shared.py
ballcosmos/cmd_tlm_server.py
ballcosmos/commands.py
ballcosmos/connection.py
ballcosmos/environment.py
ballcosmos/exceptions.py
ballcosmos/extract.py
ballcosmos/json_rpc.py
ballcosmos/limits.py
ballcosmos/replay.py
ballcosmos/scripting.py
ballcosmos/telemetry.py
ballcosmos/tools.py
ballcosmos-2.0.1.dist-info/LICENSE.txt
ballcosmos-2.0.1.dist-info/METADATA
ballcosmos-2.0.1.dist-info/WHEEL
ballcosmos-2.0.1.dist-info/entry_points.txt
ballcosmos-2.0.1.dist-info/top_level.txt
ballcosmos-2.0.1.dist-info/RECORD
