Metadata-Version: 2.1
Name: ballcosmos
Version: 2.0.1
Summary: Python Support for Ball Aerospace COSMOS v4
Home-page: https://github.com/BallAerospace/python-ballcosmos
Author: Ryan Melton
Author-email: rmelton@ball.com
License: GPLv3
Keywords: ball aerospace cosmos
Platform: UNKNOWN
Classifier: Development Status :: 4 - Beta
Classifier: Intended Audience :: Developers
Classifier: Topic :: Software Development :: Libraries :: Python Modules
Classifier: License :: OSI Approved :: GNU General Public License v3 (GPLv3)
Classifier: Programming Language :: Python :: 3.6
Classifier: Programming Language :: Python :: 3.7
Classifier: Programming Language :: Python :: 3.8
Classifier: Programming Language :: Python :: 3.9
License-File: LICENSE.txt
